{
  "reflection_id": "1520c06d-e03f-4295-8238-c1b4fcdc8c07_reflection",
  "feedback_id": "1520c06d-e03f-4295-8238-c1b4fcdc8c07",
  "ad_id": "46fbacc3-a1e9-4d78-adf4-e3dbeed18ebe",
  "brief_id": "c9ce7ec2-b065-43e2-9dd9-08614a87750a",
  "reflection": "1. Key Insights: \n   - The client appreciates humor and engagement in the ad content.\n   - The client is interested in incorporating more modern language, including slang, to connect with the target audience.\n   - The client values the use of hashtags for social media engagement and visibility.\n   - The client seems to be satisfied with the overall tone and message of the ads but seeks more ways to make them relatable and trendy.\n\n2. Strengths: \n   - The ad variations were effective in using humor and engagement to attract the target audience.\n   - The ads successfully highlighted the NYU merchandise and the new spring collection.\n   - The call-to-action in each ad was clear and compelling, encouraging the audience to shop the new collection.\n\n3. Areas for Improvement: \n   - The ads could benefit from the use of more modern language and slang to connect better with the target audience.\n   - The ads could use more hashtags to increase visibility and engagement on social media.\n\n4. Action Items: \n   - Incorporate more slang and modern language that resonates with the target audience.\n   - Use more hashtags related to NYU, spring, and the merchandise to increase visibility.\n   - Continue to use humor and engagement to attract the audience.\n   - Experiment with different hooks and highlights to keep the ads fresh and interesting.\n\n5. Pattern Recognition: \n   - The client prefers ads that are humorous, engaging, and relatable to the target audience.\n   - The client values social media engagement and visibility, as indicated by their request for more hashtags.\n   - The client is open to modern language and slang, suggesting they want to connect with a younger, more contemporary audience.",
  "created_at": "2025-04-09T11:24:15.888616",
  "structured_insights": {
    "key_insights": [
      "The client appreciates humor and engagement in the ad content.",
      "The client is interested in incorporating more modern language, including slang, to connect with the target audience.",
      "The client values the use of hashtags for social media engagement and visibility.",
      "The client seems to be satisfied with the overall tone and message of the ads but seeks more ways to make them relatable and trendy."
    ],
    "strengths": [
      "The ad variations were effective in using humor and engagement to attract the target audience.",
      "The ads successfully highlighted the NYU merchandise and the new spring collection.",
      "The call-to-action in each ad was clear and compelling, encouraging the audience to shop the new collection."
    ],
    "areas_for_improvement": [
      "The ads could benefit from the use of more modern language and slang to connect better with the target audience.",
      "The ads could use more hashtags to increase visibility and engagement on social media."
    ],
    "action_items": [
      "Incorporate more slang and modern language that resonates with the target audience.",
      "Use more hashtags related to NYU, spring, and the merchandise to increase visibility.",
      "Continue to use humor and engagement to attract the audience.",
      "Experiment with different hooks and highlights to keep the ads fresh and interesting."
    ],
    "pattern_recognition": [
      "The client prefers ads that are humorous, engaging, and relatable to the target audience.",
      "The client values social media engagement and visibility, as indicated by their request for more hashtags.",
      "The client is open to modern language and slang, suggesting they want to connect with a younger, more contemporary audience."
    ]
  }
}